sqlite_construct/__init__.py
sqlite_construct/_version.py
sqlite_construct/components.py
sqlite_construct/dbref.py
sqlite_construct-0.1.0.dist-info/LICENSE
sqlite_construct-0.1.0.dist-info/METADATA
sqlite_construct-0.1.0.dist-info/WHEEL
sqlite_construct-0.1.0.dist-info/RECORD
