Metadata-Version: 2.3
Name: sqlite-construct
Version: 0.1.0
Summary: SQLite3 database construction components
License: 0BSD
Keywords: sqlite,database
Author: ambient@mailbox.org
Requires-Python: >=3.11
Classifier: Development Status :: 4 - Beta
Classifier: License :: OSI Approved
Classifier: License :: OSI Approved :: Zero-Clause BSD (0BSD)
Classifier: Operating System :: POSIX :: Linux
Classifier: Programming Language :: Python :: 3
Classifier: Programming Language :: Python :: 3.11
Classifier: Programming Language :: Python :: 3.12
Classifier: Programming Language :: Python :: Implementation :: CPython
Classifier: Intended Audience :: Developers
Classifier: Topic :: Database
Classifier: Topic :: Software Development :: Libraries
Requires-Dist: packaging (>=25.0,<26.0)
Requires-Dist: uritools (>=4.0.3,<5.0.0)
Project-URL: Repository, https://github.com/ambient5/sqlite-construct
